retro_snake_game/__init__.py
retro_snake_game/__main__.py
retro_snake_game/snake_game.py
retro_snake_game/assets/apple.png
retro_snake_game/assets/background.png
retro_snake_game/assets/coin.wav
retro_snake_game/assets/game_over.wav
retro_snake_game/assets/game_start.wav
retro_snake_game/assets/small_apple.png
retro_snake_game/assets/snake_sheet.png
retro_snake_game/assets/sound.wav
retro_snake_game/assets/title_sound.wav
retro_snake_game/retro-font/PressStart2P-Regular.ttf
retro_snake_game-1.0.2.dist-info/licenses/LICENSE
retro_snake_game-1.0.2.dist-info/METADATA
retro_snake_game-1.0.2.dist-info/WHEEL
retro_snake_game-1.0.2.dist-info/entry_points.txt
retro_snake_game-1.0.2.dist-info/top_level.txt
retro_snake_game-1.0.2.dist-info/RECORD
