Metadata-Version: 2.4
Name: retro-snake-game
Version: 1.0.2
Summary: A retro-style snake game
Author-email: Adrian Rubio-Punal <adrian.rubio.punal@gmail.com>
License: MIT
Project-URL: Homepage, https://github.com/adrirubio/retro-snake-game
Project-URL: Repository, https://github.com/adrirubio/retro-snake-game
Project-URL: Issues, https://github.com/adrirubio/retro-snake-game/issues
Requires-Python: >=3.7
License-File: LICENSE
Requires-Dist: pygame>=2.0.0
Dynamic: license-file
